[
    {
        "name": "Дмитрий",
        "score": 0,
        "correct_answers": 0,
        "total_questions": 2,
        "time": "2025-01-26 00:05:35"
    },
    {
        "name": "Дмитрий ",
        "score": 0,
        "correct_answers": 0,
        "total_questions": 2,
        "time": "2025-01-26 00:05:47"
    },
    {
        "name": "Дмитрий ",
        "score": 0,
        "correct_answers": 0,
        "total_questions": 2,
        "time": "2025-01-26 00:05:52"
    },
    {
        "name": "Дмитрий ",
        "score": 0,
        "correct_answers": 0,
        "total_questions": 2,
        "time": "2025-01-26 00:07:01"
    },
    {
        "name": "Дмитрий",
        "score": 0,
        "correct_answers": 0,
        "total_questions": 2,
        "time": "2025-01-26 00:07:24"
    },
    {
        "name": "Дмитрий",
        "score": 50,
        "correct_answers": 1,
        "total_questions": 2,
        "time": "2025-01-26 00:12:18"
    },
    {
        "name": "Дмитрий ",
        "score": 0,
        "correct_answers": 0,
        "total_questions": 2,
        "time": "2025-01-26 00:12:32"
    },
    {
        "name": "Дмитрий ",
        "score": 50,
        "correct_answers": 1,
        "total_questions": 2,
        "time": "2025-01-26 00:12:46"
    },
    {
        "name": "Дмитрий ",
        "score": 50,
        "correct_answers": 1,
        "total_questions": 2,
        "time": "2025-01-26 00:12:58"
    },
    {
        "name": "Дмитрий ",
        "score": 50,
        "correct_answers": 1,
        "total_questions": 2,
        "time": "2025-01-26 00:13:18"
    },
    {
        "name": "Дмитрий ",
        "score": 0,
        "correct_answers": 0,
        "total_questions": 2,
        "time": "2025-01-26 00:13:41"
    },
    {
        "name": "Дмитрий ",
        "score": 0,
        "correct_answers": 0,
        "total_questions": 2,
        "time": "2025-01-26 00:13:57"
    },
    {
        "name": "www",
        "score": 0,
        "correct_answers": 0,
        "total_questions": 2,
        "time": "2025-01-26 00:14:06"
    },
    {
        "name": "Дмитрий ",
        "score": 50,
        "correct_answers": 1,
        "total_questions": 2,
        "time": "2025-01-26 00:29:00"
    },
    {
        "name": "qwee",
        "score": 0,
        "correct_answers": 0,
        "total_questions": 2,
        "time": "2025-01-26 00:42:55"
    },
    {
        "name": "ss",
        "score": 0,
        "correct_answers": 0,
        "total_questions": 2,
        "time": "2025-01-26 01:02:35"
    },
    {
        "name": "Дмитрий ",
        "score": 0,
        "correct_answers": 0,
        "total_questions": 2,
        "time": "2025-01-26 01:08:53"
    },
    {
        "name": "Дмитрий ",
        "score": 50,
        "correct_answers": 1,
        "total_questions": 2,
        "time": "2025-01-26 01:34:08"
    },
    {
        "name": "Дмитрий ",
        "score": 0,
        "correct_answers": 0,
        "total_questions": 2,
        "time": "2025-01-26 01:45:35"
    },
    {
        "name": "Дмитрий",
        "score": 0,
        "correct_answers": 0,
        "total_questions": 2,
        "time": "2025-01-26 01:48:46"
    },
    {
        "name": "Дмитрий ",
        "score": 0,
        "correct_answers": 0,
        "total_questions": 2,
        "time": "2025-01-26 01:49:13"
    },
    {
        "name": "ww",
        "score": 0,
        "correct_answers": 0,
        "total_questions": 2,
        "time": "2025-01-26 01:53:08"
    },
    {
        "name": "Дмитрий ",
        "score": 0,
        "correct_answers": 0,
        "total_questions": 2,
        "time": "2025-01-26 01:55:23"
    },
    {
        "name": "Дмитрий",
        "score": 0,
        "correct_answers": 0,
        "total_questions": 2,
        "time": "2025-01-26 01:55:53"
    },
    {
        "name": "Дмитрий ",
        "score": 0,
        "correct_answers": 0,
        "total_questions": 2,
        "time": "2025-01-26 01:57:50"
    },
    {
        "name": "Дмитрий ",
        "score": 0,
        "correct_answers": 0,
        "total_questions": 2,
        "time": "2025-01-26 02:00:56"
    },
    {
        "name": "Дмитрий ",
        "score": 0,
        "correct_answers": 0,
        "total_questions": 2,
        "time": "2025-01-26 02:01:21"
    },
    {
        "name": "Дмитрий ",
        "score": 0,
        "correct_answers": 0,
        "total_questions": 2,
        "time": "2025-01-26 02:04:06"
    },
    {
        "name": "Дмитрий ",
        "score": 0,
        "correct_answers": 0,
        "total_questions": 2,
        "time": "2025-01-26 02:04:16"
    },
    {
        "name": "Дмитрий ",
        "score": 0,
        "correct_answers": 0,
        "total_questions": 2,
        "time": "2025-01-26 02:14:24"
    },
    {
        "name": "Дмитрий ",
        "score": 100,
        "correct_answers": 2,
        "total_questions": 2,
        "time": "2025-01-26 02:41:24"
    },
    {
        "name": "15",
        "score": 50,
        "correct_answers": 1,
        "total_questions": 2,
        "time": "2025-01-26 02:57:48"
    },
    {
        "name": "5",
        "score": 0,
        "correct_answers": 0,
        "total_questions": 2,
        "time": "2025-01-26 02:57:59"
    },
    {
        "name": "111",
        "score": 0,
        "correct_answers": 0,
        "total_questions": 2,
        "time": "2025-01-26 03:04:45"
    },
    {
        "name": "Никита",
        "score": 80,
        "correct_answers": 8,
        "total_questions": 10,
        "time": "2025-01-26 03:41:41"
    },
    {
        "name": "Денис",
        "score": 90,
        "correct_answers": 9,
        "total_questions": 10,
        "time": "2025-01-26 03:44:04"
    },
    {
        "name": "Кирилл",
        "score": 100,
        "correct_answers": 10,
        "total_questions": 10,
        "time": "2025-01-26 03:46:56"
    },
    {
        "name": "Дмитрий ",
        "score": 20,
        "correct_answers": 2,
        "total_questions": 10,
        "time": "2025-01-26 04:02:22"
    },
    {
        "name": "159",
        "score": 0,
        "correct_answers": 0,
        "total_questions": 10,
        "time": "2025-01-26 15:39:06"
    },
    {
        "name": "Дмитрий",
        "score": 0,
        "correct_answers": 0,
        "total_questions": 10,
        "time": "2025-01-26 15:41:09"
    }
]